AUTHORS.rst
CONTRIBUTING.rst
HISTORY.rst
LICENSE
MANIFEST.in
README.rst
setup.cfg
setup.py
codon_harmony/__init__.py
codon_harmony/codon_harmony.py
codon_harmony.egg-info/PKG-INFO
codon_harmony.egg-info/SOURCES.txt
codon_harmony.egg-info/dependency_links.txt
codon_harmony.egg-info/entry_points.txt
codon_harmony.egg-info/not-zip-safe
codon_harmony.egg-info/requires.txt
codon_harmony.egg-info/top_level.txt
codon_harmony/data/__init__.py
codon_harmony/util/__init__.py
codon_harmony/util/codon_table_downloader.py
codon_harmony/util/codon_use.py
codon_harmony/util/logging.py
codon_harmony/util/seq.py
codon_harmony/util/seq_opt.py
docs/Makefile
docs/authors.rst
docs/codon_harmony.data.rst
docs/codon_harmony.rst
docs/codon_harmony.util.rst
docs/conf.py
docs/contributing.rst
docs/history.rst
docs/index.rst
docs/installation.rst
docs/make.bat
docs/modules.rst
docs/readme.rst
docs/usage.rst
tests/__init__.py
tests/test_codon_harmony.py
tests/test_codon_harmony_data.py
tests/test_codon_harmony_util_codon_table_downloader.py
tests/test_codon_harmony_util_codon_use.py
tests/test_codon_harmony_util_logging.py
tests/test_codon_harmony_util_seq.py
tests/test_codon_harmony_util_seq_opt.py