Metadata-Version: 1.2
Name: codon-harmony
Version: 1.0.0
Summary: Amino acid reverse translation and DNA optimization tool based on species-specific codon-use distributions.
Home-page: UNKNOWN
Author: Brian D. Weitzner
Author-email: bweitzner@lyellbio.com
License: MIT license
Keywords: codon_harmony
Platform: UNKNOWN
Classifier: Development Status :: 5 - Production/Stable
Classifier: Intended Audience :: Developers
Classifier: Intended Audience :: Science/Research
Classifier: License :: OSI Approved :: MIT License
Classifier: Natural Language :: English
Classifier: Programming Language :: Python :: 3
Classifier: Programming Language :: Python :: 3.6
Classifier: Programming Language :: Python :: 3.7
Classifier: Topic :: Scientific/Engineering
Classifier: Topic :: Scientific/Engineering :: Bio-Informatics
Requires-Python: >=3.6
